cohost/__init__.py
cohost/network.py
cohost/py.typed
cohost/models/__init__.py
cohost/models/block.py
cohost/models/comment.py
cohost/models/notification.py
cohost/models/post.py
cohost/models/project.py
cohost/models/user.py
cohost-0.5.1.dist-info/LICENSE
cohost-0.5.1.dist-info/METADATA
cohost-0.5.1.dist-info/WHEEL
cohost-0.5.1.dist-info/top_level.txt
cohost-0.5.1.dist-info/RECORD
