Metadata-Version: 2.1
Name: cohost
Version: 0.5.1
Summary: Unofficial Python API wrapper for Cohost.org - the fourth website!
Author-email: Val Knight <val@valknight.xyz>
Maintainer-email: Val Knight <val@valknight.xyz>
License: MIT License
Project-URL: repository, https://github.com/valknight/cohost.py
Keywords: cohost.org,cohost,api
Classifier: Development Status :: 2 - Pre-Alpha
Classifier: Intended Audience :: Developers
Classifier: License :: OSI Approved :: MIT License
Classifier: Programming Language :: Python :: 3 :: Only
Classifier: Programming Language :: Python :: 3.7
Classifier: Programming Language :: Python :: 3.8
Classifier: Programming Language :: Python :: 3.9
Classifier: Programming Language :: Python :: 3.10
Classifier: Programming Language :: Python :: 3.11
Classifier: Topic :: Software Development :: Libraries
Requires-Python: >=3.9
License-File: LICENSE
Requires-Dist: requests
